tamilpp/__init__.py
tamilpp/main.py
tamilpp-1.0.3.dist-info/METADATA
tamilpp-1.0.3.dist-info/WHEEL
tamilpp-1.0.3.dist-info/entry_points.txt
tamilpp-1.0.3.dist-info/top_level.txt
tamilpp-1.0.3.dist-info/RECORD
