Metadata-Version: 2.4
Name: tamilpp
Version: 1.0.3
Summary: A Python-based programming language in Tamil
Home-page: https://github.com/shrimanm/tamilpp
Author: Shriman M
Author-email: shrimanmec@gmail.com
Classifier: Programming Language :: Python :: 3
Classifier: License :: OSI Approved :: MIT License
Classifier: Operating System :: OS Independent
Requires-Python: >=3.6
Dynamic: author
Dynamic: author-email
Dynamic: classifier
Dynamic: description
Dynamic: description-content-type
Dynamic: home-page
Dynamic: requires-python
Dynamic: summary
